paper_dig/__init__.py
paper_dig/paper.py
paper_dig/keyword_extractor/__init__.py
paper_dig/keyword_extractor/keyword_extractor.py
paper_dig/keyword_extractor/simple_keyword_extractor/__init__.py
paper_dig/keyword_extractor/simple_keyword_extractor/prompts.py
paper_dig/keyword_extractor/simple_keyword_extractor/simple_keyword_extractor.py
paper_dig/markdown_extractor/__init__.py
paper_dig/markdown_extractor/datalab_extractor.py
paper_dig/markdown_extractor/markdown_extractor.py
paper_dig/paper_reader/__init__.py
paper_dig/paper_reader/paper_reader.py
paper_dig/paper_reader/prompts.py
paper_dig/summarizer/__init__.py
paper_dig/summarizer/summarizer.py
paper_dig/summarizer/semantic_summarizer/__init__.py
paper_dig/summarizer/semantic_summarizer/prompts.py
paper_dig/summarizer/semantic_summarizer/semantic_summarizer.py
paper_dig-0.2.1.dist-info/METADATA
paper_dig-0.2.1.dist-info/WHEEL
paper_dig-0.2.1.dist-info/RECORD
